RedLight/__init__.py
RedLight/api.py
RedLight/aria2_downloader.py
RedLight/async_downloader.py
RedLight/batch.py
RedLight/config.py
RedLight/converter.py
RedLight/database.py
RedLight/downloader.py
RedLight/favorites.py
RedLight/metadata.py
RedLight/multi_search.py
RedLight/notifications.py
RedLight/playlist.py
RedLight/progress_bar.py
RedLight/proxy_manager.py
RedLight/queue_manager.py
RedLight/rate_limiter.py
RedLight/resume_manager.py
RedLight/retry.py
RedLight/search.py
RedLight/server.py
RedLight/statistics.py
RedLight/system_tray.py
RedLight/version.py
RedLight/cli/__init__.py
RedLight/cli/commands.py
RedLight/cli/download.py
RedLight/cli/interactive.py
RedLight/cli/ui.py
RedLight/sites/__init__.py
RedLight/sites/base.py
RedLight/sites/eporner.py
RedLight/sites/pornhub.py
RedLight/sites/registry.py
RedLight/sites/spankbang.py
RedLight/sites/xhamster.py
RedLight/sites/xnxx.py
RedLight/sites/xvideos.py
RedLight/sites/youporn.py
ph_shorts-2.1.2.dist-info/licenses/LICENSE
ph_shorts-2.1.2.dist-info/METADATA
ph_shorts-2.1.2.dist-info/WHEEL
ph_shorts-2.1.2.dist-info/entry_points.txt
ph_shorts-2.1.2.dist-info/top_level.txt
ph_shorts-2.1.2.dist-info/RECORD
