Metadata-Version: 2.4
Name: ph-shorts
Version: 2.1.2
Summary: RedLight DL - Professional adult content downloader
Author: RedLight Team
License: MIT
Project-URL: Homepage, https://github.com/diastom/RedLightDL
Project-URL: Bug Tracker, https://github.com/diastom/RedLightDL/issues
Project-URL: Documentation, https://github.com/diastom/RedLightDL#readme
Keywords: adult,downloader,video,redlight,hls,m3u8,cli
Classifier: Development Status :: 4 - Beta
Classifier: Intended Audience :: End Users/Desktop
Classifier: Topic :: Multimedia :: Video
Classifier: License :: OSI Approved :: MIT License
Classifier: Programming Language :: Python :: 3
Classifier: Programming Language :: Python :: 3.10
Classifier: Programming Language :: Python :: 3.11
Classifier: Programming Language :: Python :: 3.12
Classifier: Operating System :: OS Independent
Classifier: Environment :: Console
Requires-Python: >=3.10
License-File: LICENSE
Requires-Dist: requests>=2.31.0
Requires-Dist: rich>=13.0.0
Requires-Dist: click>=8.1.0
Requires-Dist: beautifulsoup4>=4.12.0
Requires-Dist: pyyaml>=6.0.0
Provides-Extra: dev
Requires-Dist: pytest>=7.0.0; extra == "dev"
Requires-Dist: black>=23.0.0; extra == "dev"
Dynamic: license-file
